reggisearch/LICENSE
reggisearch/README.MD
reggisearch/__init__.py
reggisearch/requirements.txt
reggisearch/thirdparty.json
reggisearch-0.10.dist-info/LICENSE.rst
reggisearch-0.10.dist-info/METADATA
reggisearch-0.10.dist-info/WHEEL
reggisearch-0.10.dist-info/top_level.txt
reggisearch-0.10.dist-info/RECORD
